{"dport":{"email":"dport@hawaii.edu","name":"Dan Port","password":"portspassword"},"itm352":{"email":"itm352@hawaii.edu","name":"ITM 352","password":"grader"},"mkmau":{"name":"Marcus","password":"mkmau111","email":"mkmau@hawaii.edu"},"jdoe":{"name":"John Doe","password":"123John","email":"a@gmail.com"},"grego111":{"name":"Greg","password":"grego91","email":"g@gmail.com"},"hollyflax1":{"name":"holly","password":"1adrien","email":"h@gmail.com"},"bobbby1":{"name":"bobbby","password":"111bob","email":"j@gmail.com"}}